veritas/__init__.py
veritas/core/__init__.py
veritas/core/behaviors.py
veritas/core/context.py
veritas/core/evidence.py
veritas/core/mixins.py
veritas/core/verification.py
veritas/integrations/__init__.py
veritas/integrations/claude_code.py
veritas/layers/__init__.py
veritas/layers/audit.py
veritas/layers/gates.py
veritas/layers/protocol.py
veritas/schemas/__init__.py
veritas/schemas/agent_profiles.py
veritas_framework-0.1.0.dist-info/METADATA
veritas_framework-0.1.0.dist-info/WHEEL
veritas_framework-0.1.0.dist-info/licenses/LICENSE
veritas_framework-0.1.0.dist-info/RECORD
