Metadata-Version: 2.4
Name: veritas-framework
Version: 0.1.0
Summary: Trust-Based Agent Architecture for Reliable AI Systems
Project-URL: Homepage, https://github.com/RBKunnela/veritas-framework
Project-URL: Documentation, https://github.com/RBKunnela/veritas-framework#readme
Project-URL: Repository, https://github.com/RBKunnela/veritas-framework.git
Project-URL: Issues, https://github.com/RBKunnela/veritas-framework/issues
Author-email: RBKunnela <rbkunnela@example.com>
License-Expression: MIT
License-File: LICENSE
Keywords: agents,ai,audit,claude,llm,reliability,trust,verification
Classifier: Development Status :: 3 - Alpha
Classifier: Intended Audience :: Developers
Classifier: License :: OSI Approved :: MIT License
Classifier: Programming Language :: Python :: 3
Classifier: Programming Language :: Python :: 3.10
Classifier: Programming Language :: Python :: 3.11
Classifier: Programming Language :: Python :: 3.12
Classifier: Topic :: Scientific/Engineering :: Artificial Intelligence
Classifier: Topic :: Software Development :: Libraries :: Python Modules
Requires-Python: >=3.10
Requires-Dist: aiofiles>=23.0.0
Requires-Dist: pydantic>=2.0.0
Requires-Dist: structlog>=23.0.0
Provides-Extra: claude
Requires-Dist: anthropic>=0.18.0; extra == 'claude'
Provides-Extra: dev
Requires-Dist: mypy>=1.0.0; extra == 'dev'
Requires-Dist: pytest-asyncio>=0.21.0; extra == 'dev'
Requires-Dist: pytest-cov>=4.0.0; extra == 'dev'
Requires-Dist: pytest>=7.0.0; extra == 'dev'
Requires-Dist: ruff>=0.1.0; extra == 'dev'
